{
  "lastUpdate": "2018-09-01T03:42:03.150Z",
  "cowner": "dockerfile",
  "crepo": "rabbitmq",
  "totalPR": 14,
  "lastPR": {
    "createdAt": "2016-11-28T14:43:51Z",
    "username": "wahengchang"
  },
  "bestPR": {
    "user": "mattgiles",
    "nbPR": 2,
    "image": "https://avatars3.githubusercontent.com/u/4960227?v=4"
  },
  "bestMerged": {
    "user": "joelwurtz",
    "nbPR": 1,
    "image": "https://avatars3.githubusercontent.com/u/90466?v=4"
  },
  "bestRatio": {
    "user": "joelwurtz",
    "ratio": 1,
    "image": "https://avatars3.githubusercontent.com/u/90466?v=4"
  },
  "userPRInfos": {
    "wahengchang": {
      "total": 1,
      "merged": 0,
      "avatarUrl": "https://avatars0.githubusercontent.com/u/5538753?v=4"
    },
    "ivarconr": {
      "total": 1,
      "merged": 0,
      "avatarUrl": "https://avatars3.githubusercontent.com/u/158948?v=4"
    },
    "mattgiles": {
      "total": 2,
      "merged": 0,
      "avatarUrl": "https://avatars3.githubusercontent.com/u/4960227?v=4"
    },
    "StephaneC": {
      "total": 1,
      "merged": 0,
      "avatarUrl": "https://avatars0.githubusercontent.com/u/941611?v=4"
    },
    "david-resnick": {
      "total": 1,
      "merged": 0,
      "avatarUrl": "https://avatars1.githubusercontent.com/u/488086?v=4"
    },
    "pauljm": {
      "total": 1,
      "merged": 0,
      "avatarUrl": "https://avatars0.githubusercontent.com/u/1810526?v=4"
    },
    "xeor": {
      "total": 1,
      "merged": 0,
      "avatarUrl": "https://avatars3.githubusercontent.com/u/682676?v=4"
    },
    "joelwurtz": {
      "total": 1,
      "merged": 1,
      "avatarUrl": "https://avatars3.githubusercontent.com/u/90466?v=4"
    },
    "krallin": {
      "total": 1,
      "merged": 1,
      "avatarUrl": "https://avatars1.githubusercontent.com/u/1737686?v=4"
    },
    "mosheeshel": {
      "total": 1,
      "merged": 0,
      "avatarUrl": "https://avatars2.githubusercontent.com/u/1133161?v=4"
    },
    "weavejester": {
      "total": 1,
      "merged": 1,
      "avatarUrl": "https://avatars3.githubusercontent.com/u/8780?v=4"
    },
    "earthquakesan": {
      "total": 1,
      "merged": 0,
      "avatarUrl": "https://avatars0.githubusercontent.com/u/1092829?v=4"
    },
    "holmars": {
      "total": 1,
      "merged": 1,
      "avatarUrl": "https://avatars0.githubusercontent.com/u/138370?v=4"
    }
  },
  "datePRInfos": {
    "Novembre-2016": {
      "total": 1,
      "merged": 0
    },
    "Juin-2016": {
      "total": 1,
      "merged": 0
    },
    "Janvier-2016": {
      "total": 1,
      "merged": 0
    },
    "Août-2015": {
      "total": 1,
      "merged": 0
    },
    "Mai-2015": {
      "total": 1,
      "merged": 0
    },
    "Avril-2015": {
      "total": 1,
      "merged": 0
    },
    "Mars-2015": {
      "total": 1,
      "merged": 0
    },
    "Décembre-2014": {
      "total": 1,
      "merged": 0
    },
    "Novembre-2014": {
      "total": 1,
      "merged": 1
    },
    "Octobre-2014": {
      "total": 1,
      "merged": 1
    },
    "Septembre-2014": {
      "total": 4,
      "merged": 2
    }
  }
}